amdfan/__init__.py
amdfan/__main__.py
amdfan/commands.py
amdfan/config.py
amdfan/controller.py
amdfan/defaults.py
amdfan-0.2.5.dist-info/LICENSE
amdfan-0.2.5.dist-info/METADATA
amdfan-0.2.5.dist-info/WHEEL
amdfan-0.2.5.dist-info/entry_points.txt
amdfan-0.2.5.dist-info/RECORD
