Metadata-Version: 2.3
Name: amdfan
Version: 0.2.5
Summary: Fan monitor and controller for AMD gpus in Linux
License: GPL-2.0-only
Keywords: fan,gpu,temp,monitor,amd
Author: mcgillij
Author-email: mcgillivray.jason@gmail.com
Requires-Python: >=3.11,<4.0
Classifier: Environment :: Console
Classifier: Environment :: GPU
Classifier: Intended Audience :: End Users/Desktop
Classifier: License :: OSI Approved :: GNU General Public License v2 (GPLv2)
Classifier: Natural Language :: English
Classifier: Operating System :: POSIX :: Linux
Classifier: Programming Language :: Python :: 3
Classifier: Programming Language :: Python :: 3.11
Classifier: Programming Language :: Python :: 3.12
Classifier: Programming Language :: Python :: 3.13
Classifier: Topic :: System :: Boot :: Init
Classifier: Topic :: System :: Hardware
Classifier: Topic :: System :: Monitoring
Classifier: Topic :: Utilities
Requires-Dist: click (>=8.1.3,<9.0.0)
Requires-Dist: numpy (>=2.0.0,<3.0.0)
Requires-Dist: pyyaml (>=6.0,<7.0)
Requires-Dist: rich (>=14.0.0,<15.0.0)
Project-URL: Documentation, https://mcgillij.dev/pages/amdfan.html
Project-URL: Homepage, https://mcgillij.dev/pages/amdfan.html
Project-URL: Repository, https://github.com/mcgillij/amdfan
